context_managed_singleton/__init__.py
context_managed_singleton-1.0.0.dist-info/METADATA
context_managed_singleton-1.0.0.dist-info/WHEEL
context_managed_singleton-1.0.0.dist-info/RECORD
