Metadata-Version: 2.1
Name: context-managed-singleton
Version: 1.0.0
Summary: Simple stack-based, context managed singleton-ish utility
Home-page: https://github.com/Limboid/context-managed-singleton
License: MIT
Keywords: singleton
Author: Jacob Valdez
Author-email: jacob.valdez@limboid.ai
Requires-Python: >=3.8,<4.0
Classifier: License :: OSI Approved :: MIT License
Classifier: Programming Language :: Python :: 3
Classifier: Programming Language :: Python :: 3.8
Classifier: Programming Language :: Python :: 3.9
Classifier: Programming Language :: Python :: 3.10
Classifier: Programming Language :: Python :: 3.11
Classifier: Topic :: Software Development :: Libraries :: Python Modules
Project-URL: Repository, https://github.com/Limboid/context-managed-singleton
